ImageKit/ImgKit.py
ImageKit/__init__.py
Image_Kit-0.0.3.dist-info/LICENSE
Image_Kit-0.0.3.dist-info/METADATA
Image_Kit-0.0.3.dist-info/WHEEL
Image_Kit-0.0.3.dist-info/top_level.txt
Image_Kit-0.0.3.dist-info/RECORD
