Metadata-Version: 2.1
Name: Image-Kit
Version: 0.0.3
Summary: A module for basic image processing.
Home-page: https://github.com/syamkakarla98/Image-Kit
Author: Syam Kakarla
Author-email: Syamkakarla98@gmail.com
License: MIT
Platform: UNKNOWN
Classifier: Programming Language :: Python :: 3
Classifier: License :: OSI Approved :: MIT License
Classifier: Operating System :: OS Independent
Requires-Python: >=3.5.3
